{
  "type": "forge:conditional",
  "recipes": [
    {
      "conditions": [
        {
          "type": "reliquary:mob_drops_craftable"
        }
      ],
      "recipe": {
        "type": "minecraft:crafting_shaped",
        "key": {
          "G": {
            "tag": "forge:ingots/gold"
          },
          "P": {
            "item": "minecraft:pumpkin"
          },
          "S": {
            "item": "minecraft:snow"
          }
        },
        "pattern": [
          "GPG",
          "GSG",
          "GSG"
        ],
        "result": {
          "item": "reliquary:frozen_core"
        }
      }
    }
  ]
}